temporal/__init__.py
temporal/main.py
temporal/util.py
tests/__init__.py
tests/test_limited_dict.py
tests/test_temporal.py
temporalobject-0.2.0.dist-info/LICENSE
temporalobject-0.2.0.dist-info/METADATA
temporalobject-0.2.0.dist-info/WHEEL
temporalobject-0.2.0.dist-info/top_level.txt
temporalobject-0.2.0.dist-info/RECORD
