Metadata-Version: 2.1
Name: temporalobject
Version: 0.2.0
Summary: A custom python object for storing and managing states in a temporal sequence.
Home-page: https://pypi.org/project/temporalobject/
Author: Chris Mangum
Author-email: csmangum@gmail.com
Classifier: Programming Language :: Python :: 3
Classifier: License :: OSI Approved :: MIT License
Classifier: Operating System :: OS Independent
Requires-Python: >=3.10
License-File: LICENSE
